geovis_upload_sdk/__init__.py
geovis_upload_sdk/sign.py
geovis_upload_sdk/upload.py
geovis_upload_sdk-0.0.3.dist-info/LICENSE
geovis_upload_sdk-0.0.3.dist-info/METADATA
geovis_upload_sdk-0.0.3.dist-info/WHEEL
geovis_upload_sdk-0.0.3.dist-info/top_level.txt
geovis_upload_sdk-0.0.3.dist-info/RECORD
