Metadata-Version: 2.1
Name: geovis-upload-sdk
Version: 0.0.3
Summary: geovis upload file sdk
Home-page: https://github.com/kevinxuelei
Author: kevinxuelei
Author-email: kevinxuelei <kevinxuelei@163.com>
Project-URL: Homepage, https://github.com/pypa/sampleproject
Project-URL: Bug Tracker, https://github.com/pypa/sampleproject/issues
Keywords: python,menu,dumb_menu,windows,mac,linux
Classifier: Programming Language :: Python :: 3
Classifier: License :: OSI Approved :: MIT License
Classifier: Operating System :: OS Independent
Requires-Python: >=3.7
License-File: LICENSE
